pynetcor/cluster.py
pynetcor/cor.py
pynetcor/_core.cp311-win_amd64.pyd
pynetcor/__init__.py
pynetcor-0.1.1.dist-info/DELVEWHEEL
pynetcor-0.1.1.dist-info/METADATA
pynetcor-0.1.1.dist-info/RECORD
pynetcor-0.1.1.dist-info/top_level.txt
pynetcor-0.1.1.dist-info/WHEEL
pynetcor.libs/msvcp140-3a896538a89087f2c20e9f8bfde34d88.dll
pynetcor.libs/netcor-4eb807a161fdda6392e019da45b4158b.dll
pynetcor.libs/openblas-8f94a7aff39368c3783c182a3c158f60.dll
pynetcor.libs/vcomp140-a902e8d63345fbcd62c1419f09820050.dll
