Metadata-Version: 2.1
Name: pynetcor
Version: 0.1.1
Summary: PyNetCor is a fast Python C++ extension for correlation and network analysis
Home-page: https://github.com/01life/pyNetCor
Author: longshibin
Author-email: longshibin@01lifetech.com
License: MIT
Classifier: Programming Language :: C++
Classifier: Programming Language :: Python :: 3
Classifier: Programming Language :: Python :: 3.7
Classifier: Programming Language :: Python :: 3.8
Classifier: Programming Language :: Python :: 3.9
Classifier: Programming Language :: Python :: 3.10
Classifier: Programming Language :: Python :: 3.11
Classifier: Programming Language :: Python :: 3.12
Classifier: License :: OSI Approved :: MIT License
Classifier: Operating System :: OS Independent
Requires-Python: >=3.7
Requires-Dist: numpy
